{"thesis_id": "THESIS-BOJ-YEN-CARRY-UNWIND", "generated_at": "2026-07-18 14:50 SGT", "status": "WATCH", "score": 30.0, "yen_carry_unwind_status": "WATCH", "usd_jpy": {"price": 162.353, "change_5m_pct": -0.0259, "change_15m_pct": -0.0326, "change_1h_pct": -0.0166, "breakdown_flag": false, "data_source": "intraday_1m", "note": ""}, "boj_statement": {"status": "DETECTED", "score": 2.0, "boj_statement_detected": true, "tone": "DOVISH", "hawkish_count": 0, "dovish_count": 1, "evidence": ["[D] '据え置き' — Google_News_JP_BOJ: 沖縄県内の景気「拡大基調にある」 日銀那覇支店が32カ月連続で判断据え置き 2026年7月【主要指標の推移グラフ】 - 沖縄タイムス社…"]}, "boj_tone_gate": {"status": "DOVISH", "score": 2.0, "tone": "DOVISH", "hawkish_count": 0, "dovish_count": 1}, "usd_jpy_gate": {"status": "CALM", "score": 2.0, "price": 162.353, "change_5m_pct": -0.0259, "change_15m_pct": -0.0326, "change_1h_pct": -0.0166, "breakdown_flag": false, "data_source": "intraday_1m", "note": ""}, "japan_equity_gate": {"status": "ACTIVE", "score": 6.0, "ewj_change_pct": -1.545, "dxj_change_pct": -1.996}, "volatility_gate": {"status": "SPIKE", "score": 12.0, "vxx_change_pct": 4.802, "vixy_change_pct": 5.302, "uvxy_change_pct": 8.811}, "us_equity_gate": {"status": "ACTIVE", "score": 6.0, "spy_change_pct": -0.99, "qqq_change_pct": -1.503, "iwm_change_pct": -0.524}, "credit_gate": {"status": "CALM", "score": 0.0, "hyg_change_pct": -0.188, "jnk_change_pct": -0.104, "lqd_change_pct": 0.056}, "high_beta_gate": {"status": "CALM", "score": 0.0, "nvda_change_pct": -2.213, "asts_change_pct": 5.072, "qbts_change_pct": -1.123, "qubt_change_pct": 2.094, "ionq_change_pct": -0.912, "rklb_change_pct": 0.401, "lunr_change_pct": 0.595, "pl_change_pct": 1.72}, "intraday_usdjpy": {"price": 162.353, "change_5m_pct": -0.0259, "change_15m_pct": -0.0326, "change_1h_pct": -0.0166, "breakdown_flag": false, "data_source": "intraday_1m", "note": ""}, "cio_action": "HOLD_HEDGE", "blocked_actions": ["BLOCK_SECOND_TRANCHE", "BUY", "CANCEL_ORDER", "EXECUTE", "ROUTE_ORDER", "SELL"], "alerts": ["ALERT: EWJ -1.5% — Japan equity selling off, watch carry positions"], "notes": [], "human_summary": "BOJ/Yen Carry Event Watcher: status WATCH (score 30.0/100) — USD/JPY 1h change -0.017%, yen carry unwind WATCH, BOJ tone DOVISH, CIO action HOLD_HEDGE."}