{
  "generated_at": "2026-07-02T17:16:40+08:00",
  "portfolio_updated_at": "2026-07-02T17:16:40+08:00",
  "source": "moomoo_direct",
  "regime_short": "MILD RISK OFF",
  "regime_score": "-1",
  "regime_color": "#ff5566",
  "regime_emoji": "🔴",
  "cio_action": "WAIT / HOLD",
  "vix": "16.72",
  "vix_alert": false,
  "fg_score": 30.5,
  "fg_label": "FEAR",
  "fg_color": "#fbbf24",
  "market_val": 30006.73,
  "market_val_fmt": "$30,006.73",
  "total_pnl": -424.56,
  "total_pnl_pct": -1.395,
  "pnl_fmt": "$-424.56",
  "pnl_color": "#ff5566",
  "cash": 23113.54,
  "cash_fmt": "$23,113.54",
  "cash_pct": 43.51,
  "cash_pct_fmt": "43.5%",
  "cash_color": "#4ade80",
  "integrity": "PASS",
  "integrity_color": "#4ade80",
  "positions": [
    {
      "ticker": "WFC",
      "qty": 40.0,
      "price": 86.52,
      "avg_price": 83.41,
      "avg_cost": 83.41,
      "cost_basis": 3336.4,
      "chg_pct": null,
      "unrealized": 124.41,
      "unrealized_p": 3.73,
      "thesis": "BANKS"
    },
    {
      "ticker": "VXX",
      "qty": 70.0,
      "price": 22.32,
      "avg_price": 22.632,
      "avg_cost": 22.632,
      "cost_basis": 1584.24,
      "chg_pct": null,
      "unrealized": -21.82,
      "unrealized_p": -1.38,
      "thesis": "VOL_HEDGE"
    },
    {
      "ticker": "VIXY",
      "qty": 160.0,
      "price": 21.49,
      "avg_price": 22.493,
      "avg_cost": 22.493,
      "cost_basis": 3598.88,
      "chg_pct": null,
      "unrealized": -160.4,
      "unrealized_p": -4.46,
      "thesis": "VOL_HEDGE"
    },
    {
      "ticker": "NVDA",
      "qty": 10.0,
      "price": 196.02,
      "avg_price": 199.25,
      "avg_cost": 199.25,
      "cost_basis": 1992.5,
      "chg_pct": null,
      "unrealized": -32.27,
      "unrealized_p": -1.62,
      "thesis": "AI"
    },
    {
      "ticker": "NEM",
      "qty": 40.0,
      "price": 94.66,
      "avg_price": 97.833,
      "avg_cost": 97.833,
      "cost_basis": 3913.32,
      "chg_pct": null,
      "unrealized": -126.93,
      "unrealized_p": -3.24,
      "thesis": "GOLD"
    },
    {
      "ticker": "BAC",
      "qty": 50.0,
      "price": 58.69,
      "avg_price": 57.172,
      "avg_cost": 57.172,
      "cost_basis": 2858.6,
      "chg_pct": null,
      "unrealized": 75.9,
      "unrealized_p": 2.66,
      "thesis": "BANKS"
    },
    {
      "ticker": "B",
      "qty": 110.0,
      "price": 37.02,
      "avg_price": 38.069,
      "avg_cost": 38.069,
      "cost_basis": 4187.59,
      "chg_pct": null,
      "unrealized": -115.43,
      "unrealized_p": -2.76,
      "thesis": "GOLD"
    },
    {
      "ticker": "AU",
      "qty": 50.0,
      "price": 82.08,
      "avg_price": 82.934,
      "avg_cost": 82.934,
      "cost_basis": 4146.7,
      "chg_pct": null,
      "unrealized": -42.69,
      "unrealized_p": -1.03,
      "thesis": "GOLD"
    },
    {
      "ticker": "AEM",
      "qty": 30.0,
      "price": 156.26,
      "avg_price": 160.438,
      "avg_cost": 160.438,
      "cost_basis": 4813.14,
      "chg_pct": null,
      "unrealized": -125.33,
      "unrealized_p": -2.6,
      "thesis": "GOLD"
    }
  ],
  "top_movers": [
    {
      "ticker": "SPY",
      "price": 745.76,
      "chg_pct": 0.0,
      "open": 745.0,
      "high": 749.43,
      "low": 742.38,
      "volume": 47100878
    },
    {
      "ticker": "QQQ",
      "price": 725.17,
      "chg_pct": 0.0,
      "open": 729.19,
      "high": 731.92,
      "low": 724.6,
      "volume": 40803791
    },
    {
      "ticker": "IWM",
      "price": 299.32,
      "chg_pct": 0.0,
      "open": 299.93,
      "high": 302.72,
      "low": 298.92,
      "volume": 20607882
    },
    {
      "ticker": "TLT",
      "price": 85.52,
      "chg_pct": 0.0,
      "open": 85.48,
      "high": 85.79,
      "low": 85.42,
      "volume": 28109797
    },
    {
      "ticker": "GLD",
      "price": 370.6,
      "chg_pct": 0.0,
      "open": 371.2,
      "high": 377.78,
      "low": 370.21,
      "volume": 9058287
    },
    {
      "ticker": "UUP",
      "price": 28.49,
      "chg_pct": 0.0,
      "open": 28.48,
      "high": 28.49,
      "low": 28.42,
      "volume": 1996384
    },
    {
      "ticker": "ASTS",
      "price": 86.1,
      "chg_pct": 0.0,
      "open": 86.91,
      "high": 91.81,
      "low": 83.4,
      "volume": 18219281
    },
    {
      "ticker": "RKLB",
      "price": 100.07,
      "chg_pct": 0.0,
      "open": 101.19,
      "high": 107.6,
      "low": 97.62,
      "volume": 21668009
    },
    {
      "ticker": "RDW",
      "price": 11.97,
      "chg_pct": 0.0,
      "open": 12.0,
      "high": 12.82,
      "low": 11.88,
      "volume": 21964043
    },
    {
      "ticker": "LUNR",
      "price": 20.2,
      "chg_pct": 0.0,
      "open": 21.86,
      "high": 22.08,
      "low": 20.17,
      "volume": 15484214
    }
  ],
  "market_signals": {
    "spy_chg": 0.0,
    "qqq_chg": 0.0,
    "iwm_chg": 0.0,
    "tlt_chg": 0.0,
    "gld_chg": 0.0,
    "uup_chg": 0.0,
    "defensive_avg": 0.0,
    "growth_avg": 0.0,
    "sentiment": "NEUTRAL",
    "sentiment_color": "#94a3b8"
  }
}