{"generated_at": "2026-06-16T10:42:21", "regime_short": "NEUTRAL", "regime_score": "0", "regime_color": "#fbbf24", "regime_emoji": "🟡", "cio_action": "HOLD / WAIT", "vix": "16.2", "vix_alert": false, "fg_score": 40.9, "fg_label": "FEAR", "fg_color": "#fbbf24", "market_val": 2509.46, "market_val_fmt": "$2,509.46", "total_pnl": 40.86, "total_pnl_pct": 1.612, "pnl_fmt": "$40.86 (+1.6%)", "pnl_color": "#4ade80", "cash": 55588.01, "cash_fmt": "$55,588.01", "cash_pct": 95.68, "cash_pct_fmt": "95.7%", "cash_color": "#4ade80", "integrity": "PASS", "integrity_color": "#4ade80", "positions": [{"ticker": "VIXY", "qty": 50.0, "price": 21.81, "chg_pct": 0.0, "market_val": 1090.5, "unrealized": -3.52, "unrealized_p": -0.32, "pnl_integrity_status": "OK", "thesis": "WATCH"}, {"ticker": "VXX", "qty": 36.0, "price": 22.69, "chg_pct": 0.0, "market_val": 816.84, "unrealized": 1.53, "unrealized_p": 0.19, "pnl_integrity_status": "OK", "thesis": "WATCH"}, {"ticker": "QBTS", "qty": 10.0, "price": 26.28, "chg_pct": 0.0, "market_val": 262.8, "unrealized": 78.32, "unrealized_p": 42.45, "pnl_integrity_status": "BROKER_PNL_SOURCE_CONFLICT", "thesis": "WATCH"}, {"ticker": "LUNR", "qty": 9.0, "price": 25.38, "chg_pct": 0.0, "market_val": 228.42, "unrealized": 12.27, "unrealized_p": 5.68, "pnl_integrity_status": "BROKER_PNL_SOURCE_CONFLICT", "thesis": "WATCH"}, {"ticker": "QUBT", "qty": 10.0, "price": 11.09, "chg_pct": 0.0, "market_val": 110.9, "unrealized": -47.74, "unrealized_p": -30.09, "pnl_integrity_status": "BROKER_PNL_SOURCE_CONFLICT", "thesis": "WATCH"}]}