{"generated_at": "2026-06-19T06:47:49", "regime_short": "MILD RISK OFF", "regime_score": "-2", "regime_color": "#ff5566", "regime_emoji": "🔴", "cio_action": "WAIT / HOLD", "vix": "16.4", "vix_alert": false, "fg_score": 37.5, "fg_label": "FEAR", "fg_color": "#fbbf24", "market_val": 22848.48, "market_val_fmt": "$22,848.48", "total_pnl": 246.46, "total_pnl_pct": 1.087, "pnl_fmt": "$246.46 (+1.1%)", "pnl_color": "#4ade80", "cash": 35426.63, "cash_fmt": "$35,426.63", "cash_pct": 60.79, "cash_pct_fmt": "60.8%", "cash_color": "#4ade80", "integrity": "PASS", "integrity_color": "#4ade80", "positions": [{"ticker": "ASTS", "qty": 80.0, "price": 80.22, "chg_pct": 0.0, "market_val": 6417.67, "unrealized": 96.1, "unrealized_p": 1.52, "pnl_integrity_status": "BROKER_PNL_SOURCE_CONFLICT", "thesis": "WATCH"}, {"ticker": "PL", "qty": 100.0, "price": 28.15, "chg_pct": 0.0, "market_val": 2815.0, "unrealized": 79.78, "unrealized_p": 2.92, "pnl_integrity_status": "OK", "thesis": "WATCH"}, {"ticker": "QUBT", "qty": 200.0, "price": 10.6, "chg_pct": 0.0, "market_val": 2120.0, "unrealized": -53.26, "unrealized_p": -2.45, "pnl_integrity_status": "BROKER_PNL_SOURCE_CONFLICT", "thesis": "WATCH"}, {"ticker": "LUNR", "qty": 80.0, "price": 22.71, "chg_pct": 0.0, "market_val": 1817.04, "unrealized": 31.44, "unrealized_p": 1.76, "pnl_integrity_status": "BROKER_PNL_SOURCE_CONFLICT", "thesis": "WATCH"}, {"ticker": "QBTS", "qty": 70.0, "price": 24.47, "chg_pct": 0.0, "market_val": 1712.9, "unrealized": 89.42, "unrealized_p": 5.51, "pnl_integrity_status": "BROKER_PNL_SOURCE_CONFLICT", "thesis": "WATCH"}, {"ticker": "RDW", "qty": 100.0, "price": 14.24, "chg_pct": 0.0, "market_val": 1424.0, "unrealized": -3.5, "unrealized_p": -0.25, "pnl_integrity_status": "OK", "thesis": "WATCH"}, {"ticker": "VXX", "qty": 50.0, "price": 22.76, "chg_pct": 0.0, "market_val": 1138.0, "unrealized": 5.9, "unrealized_p": 0.52, "pnl_integrity_status": "OK", "thesis": "WATCH"}, {"ticker": "BAC", "qty": 20.0, "price": 56.23, "chg_pct": 0.0, "market_val": 1124.6, "unrealized": -2.2, "unrealized_p": -0.2, "pnl_integrity_status": "OK", "thesis": "WATCH"}, {"ticker": "VIXY", "qty": 50.0, "price": 22.0, "chg_pct": 0.0, "market_val": 1100.0, "unrealized": 5.98, "unrealized_p": 0.55, "pnl_integrity_status": "OK", "thesis": "WATCH"}, {"ticker": "WFC", "qty": 13.0, "price": 82.49, "chg_pct": 0.0, "market_val": 1072.37, "unrealized": -6.2, "unrealized_p": -0.57, "pnl_integrity_status": "OK", "thesis": "WATCH"}, {"ticker": "RKLB", "qty": 10.0, "price": 105.99, "chg_pct": 0.0, "market_val": 1059.9, "unrealized": 18.0, "unrealized_p": 1.73, "pnl_integrity_status": "OK", "thesis": "WATCH"}, {"ticker": "SPCE", "qty": 300.0, "price": 3.49, "chg_pct": 0.0, "market_val": 1047.0, "unrealized": -15.0, "unrealized_p": -1.41, "pnl_integrity_status": "OK", "thesis": "WATCH"}]}