{"generated_at": "2026-06-25T14:42:45", "portfolio_updated_at": "2026-06-25T14:42:45", "source": "dataset_raw", "regime_short": "NEUTRAL", "regime_score": "0", "regime_color": "#fbbf24", "regime_emoji": "🟡", "cio_action": "HOLD / WAIT", "vix": "18.65", "vix_alert": false, "fg_score": 26.0, "fg_label": "FEAR", "fg_color": "#ff5566", "market_val": 49918.47, "market_val_fmt": "$49,918.47", "total_pnl": -2203.4, "total_pnl_pct": -4.211, "pnl_fmt": "$-2,203.40 (-4.2%)", "pnl_color": "#ff5566", "cash": 5821.06, "cash_fmt": "$5,821.06", "cash_pct": 10.44, "cash_pct_fmt": "10.4%", "cash_color": "#ff5566", "integrity": "PASS", "integrity_color": "#4ade80", "positions": [{"ticker": "ASTS", "qty": 180.0, "price": 69.36, "avg_price": 73.722, "avg_cost": 73.722, "chg_pct": 0.0, "market_val": 12484.8, "cost_basis": 13269.96, "unrealized": -813.85, "unrealized_p": -6.12, "pnl_integrity_status": "BROKER_REPORTED", "thesis": "SPACE"}, {"ticker": "PL", "qty": 225.0, "price": 26.2, "avg_price": 27.233, "avg_cost": 27.233, "chg_pct": 0.0, "market_val": 5895.0, "cost_basis": 6127.43, "unrealized": -106.24, "unrealized_p": -1.77, "pnl_integrity_status": "BROKER_REPORTED", "thesis": "SPACE"}, {"ticker": "RKLB", "qty": 65.0, "price": 86.26, "avg_price": 93.329, "avg_cost": 93.329, "chg_pct": 0.0, "market_val": 5606.9, "cost_basis": 6066.39, "unrealized": -450.31, "unrealized_p": -7.43, "pnl_integrity_status": "BROKER_REPORTED", "thesis": "SPACE"}, {"ticker": "LUNR", "qty": 250.0, "price": 19.36, "avg_price": 20.542, "avg_cost": 20.542, "chg_pct": 0.0, "market_val": 4840.0, "cost_basis": 5135.5, "unrealized": -255.44, "unrealized_p": -5.01, "pnl_integrity_status": "BROKER_REPORTED", "thesis": "SPACE"}, {"ticker": "QBTS", "qty": 150.0, "price": 23.54, "avg_price": 23.146, "avg_cost": 23.146, "chg_pct": 0.0, "market_val": 3531.0, "cost_basis": 3471.9, "unrealized": 59.08, "unrealized_p": 1.7, "pnl_integrity_status": "BROKER_REPORTED", "thesis": "QUANTUM"}, {"ticker": "RDW", "qty": 300.0, "price": 11.37, "avg_price": 12.301, "avg_cost": 12.301, "chg_pct": 0.0, "market_val": 3411.0, "cost_basis": 3690.3, "unrealized": -307.91, "unrealized_p": -8.28, "pnl_integrity_status": "BROKER_REPORTED", "thesis": "SPACE"}, {"ticker": "QUBT", "qty": 300.0, "price": 9.98, "avg_price": 9.913, "avg_cost": 9.913, "chg_pct": 0.0, "market_val": 2994.0, "cost_basis": 2973.9, "unrealized": 20.0, "unrealized_p": 0.68, "pnl_integrity_status": "BROKER_REPORTED", "thesis": "QUANTUM"}, {"ticker": "NVDA", "qty": 10.0, "price": 200.65, "avg_price": 199.25, "avg_cost": 199.25, "chg_pct": 0.0, "market_val": 2006.5, "cost_basis": 1992.5, "unrealized": 14.0, "unrealized_p": 0.7, "pnl_integrity_status": "BROKER_REPORTED", "thesis": "AI"}, {"ticker": "AEM", "qty": 11.0, "price": 152.7, "avg_price": 164.157, "avg_cost": 164.157, "chg_pct": 0.0, "market_val": 1679.7, "cost_basis": 1805.73, "unrealized": -126.03, "unrealized_p": -6.98, "pnl_integrity_status": "BROKER_REPORTED", "thesis": "GOLD"}, {"ticker": "NEM", "qty": 18.0, "price": 92.79, "avg_price": 100.004, "avg_cost": 100.004, "chg_pct": 0.0, "market_val": 1670.22, "cost_basis": 1800.07, "unrealized": -129.85, "unrealized_p": -7.21, "pnl_integrity_status": "BROKER_REPORTED", "thesis": "GOLD"}, {"ticker": "AU", "qty": 20.0, "price": 78.64, "avg_price": 84.36, "avg_cost": 84.36, "chg_pct": 0.0, "market_val": 1572.8, "cost_basis": 1687.2, "unrealized": -114.39, "unrealized_p": -6.78, "pnl_integrity_status": "BROKER_REPORTED", "thesis": "GOLD"}, {"ticker": "B", "qty": 42.0, "price": 36.31, "avg_price": 39.439, "avg_cost": 39.439, "chg_pct": 0.0, "market_val": 1525.02, "cost_basis": 1656.44, "unrealized": -131.42, "unrealized_p": -7.93, "pnl_integrity_status": "BROKER_REPORTED", "thesis": "GOLD"}, {"ticker": "BAC", "qty": 20.0, "price": 57.72, "avg_price": 56.34, "avg_cost": 56.34, "chg_pct": 0.0, "market_val": 1154.4, "cost_basis": 1126.8, "unrealized": 27.6, "unrealized_p": 2.45, "pnl_integrity_status": "BROKER_REPORTED", "thesis": "BANKS"}, {"ticker": "WFC", "qty": 13.0, "price": 84.21, "avg_price": 82.967, "avg_cost": 82.967, "chg_pct": 0.0, "market_val": 1094.73, "cost_basis": 1078.57, "unrealized": 16.16, "unrealized_p": 1.5, "pnl_integrity_status": "BROKER_REPORTED", "thesis": "BANKS"}, {"ticker": "VXX", "qty": 10.0, "price": 23.04, "avg_price": 22.642, "avg_cost": 22.642, "chg_pct": 0.0, "market_val": 230.4, "cost_basis": 226.42, "unrealized": 49.74, "unrealized_p": 27.53, "pnl_integrity_status": "BROKER_REPORTED", "thesis": "VOL_HEDGE"}, {"ticker": "VIXY", "qty": 10.0, "price": 22.2, "avg_price": 21.88, "avg_cost": 21.88, "chg_pct": 0.0, "market_val": 222.0, "cost_basis": 218.8, "unrealized": 45.46, "unrealized_p": 25.75, "pnl_integrity_status": "BROKER_REPORTED", "thesis": "VOL_HEDGE"}]}