{
  "generated_at": "2026-06-21T07:57:20",
  "portfolio_updated_at": "2026-06-21T07:57:20",
  "source": "moomoo_direct",
  "regime_short": "NEUTRAL",
  "regime_score": "0",
  "regime_color": "#fbbf24",
  "regime_emoji": "🟡",
  "cio_action": "HOLD / WAIT",
  "vix": "16.78",
  "vix_alert": false,
  "fg_score": 37.3,
  "fg_label": "FEAR",
  "fg_color": "#fbbf24",
  "market_val": 22987.1,
  "market_val_fmt": "$22,987.10",
  "total_pnl": 385.08,
  "total_pnl_pct": 1.698,
  "pnl_fmt": "$385.08",
  "pnl_color": "#4ade80",
  "cash": 35426.63,
  "cash_fmt": "$35,426.63",
  "cash_pct": 60.65,
  "cash_pct_fmt": "60.6%",
  "cash_color": "#4ade80",
  "integrity": "PASS",
  "integrity_color": "#4ade80",
  "positions": [
    {
      "ticker": "WFC",
      "qty": 13.0,
      "price": 82.2,
      "avg_price": 82.967,
      "avg_cost": 82.967,
      "cost_basis": 1078.57,
      "chg_pct": null,
      "unrealized": -9.97,
      "unrealized_p": -0.92,
      "thesis": "BANKS"
    },
    {
      "ticker": "VXX",
      "qty": 50.0,
      "price": 22.8,
      "avg_price": 22.642,
      "avg_cost": 22.642,
      "cost_basis": 1132.1,
      "chg_pct": null,
      "unrealized": 7.9,
      "unrealized_p": 0.7,
      "thesis": "VOL_HEDGE"
    },
    {
      "ticker": "VIXY",
      "qty": 50.0,
      "price": 21.9,
      "avg_price": 21.88,
      "avg_cost": 21.88,
      "cost_basis": 1094.0,
      "chg_pct": null,
      "unrealized": 0.98,
      "unrealized_p": 0.09,
      "thesis": "VOL_HEDGE"
    },
    {
      "ticker": "SPCE",
      "qty": 300.0,
      "price": 3.56,
      "avg_price": 3.54,
      "avg_cost": 3.54,
      "cost_basis": 1062.0,
      "chg_pct": null,
      "unrealized": 6.0,
      "unrealized_p": 0.56,
      "thesis": "SPACE"
    },
    {
      "ticker": "RKLB",
      "qty": 10.0,
      "price": 107.24,
      "avg_price": 104.19,
      "avg_cost": 104.19,
      "cost_basis": 1041.9,
      "chg_pct": null,
      "unrealized": 30.5,
      "unrealized_p": 2.93,
      "thesis": "SPACE"
    },
    {
      "ticker": "RDW",
      "qty": 100.0,
      "price": 14.35,
      "avg_price": 14.275,
      "avg_cost": 14.275,
      "cost_basis": 1427.5,
      "chg_pct": null,
      "unrealized": 7.5,
      "unrealized_p": 0.53,
      "thesis": "SPACE"
    },
    {
      "ticker": "QUBT",
      "qty": 200.0,
      "price": 10.76,
      "avg_price": 10.653,
      "avg_cost": 10.653,
      "cost_basis": 2130.6,
      "chg_pct": null,
      "unrealized": -21.26,
      "unrealized_p": -0.98,
      "thesis": "QUANTUM"
    },
    {
      "ticker": "QBTS",
      "qty": 70.0,
      "price": 24.69,
      "avg_price": 24.539,
      "avg_cost": 24.539,
      "cost_basis": 1717.73,
      "chg_pct": null,
      "unrealized": 104.82,
      "unrealized_p": 6.45,
      "thesis": "QUANTUM"
    },
    {
      "ticker": "PL",
      "qty": 100.0,
      "price": 28.23,
      "avg_price": 27.352,
      "avg_cost": 27.352,
      "cost_basis": 2735.2,
      "chg_pct": null,
      "unrealized": 87.78,
      "unrealized_p": 3.21,
      "thesis": "SPACE"
    },
    {
      "ticker": "LUNR",
      "qty": 80.0,
      "price": 22.85,
      "avg_price": 22.501,
      "avg_cost": 22.501,
      "cost_basis": 1800.08,
      "chg_pct": null,
      "unrealized": 42.4,
      "unrealized_p": 2.37,
      "thesis": "SPACE"
    },
    {
      "ticker": "BAC",
      "qty": 20.0,
      "price": 56.2,
      "avg_price": 56.34,
      "avg_cost": 56.34,
      "cost_basis": 1126.8,
      "chg_pct": null,
      "unrealized": -2.8,
      "unrealized_p": -0.25,
      "thesis": "BANKS"
    },
    {
      "ticker": "ASTS",
      "qty": 80.0,
      "price": 80.66,
      "avg_price": 79.141,
      "avg_cost": 79.141,
      "cost_basis": 6331.28,
      "chg_pct": null,
      "unrealized": 131.23,
      "unrealized_p": 2.08,
      "thesis": "SPACE"
    }
  ],
  "top_movers": [
    {
      "ticker": "SPY",
      "price": 746.74,
      "chg_pct": 0.0,
      "open": 747.76,
      "high": 748.23,
      "low": 743.86,
      "volume": 80875657
    },
    {
      "ticker": "QQQ",
      "price": 740.62,
      "chg_pct": 0.0,
      "open": 737.2,
      "high": 741.82,
      "low": 732.51,
      "volume": 50154595
    },
    {
      "ticker": "IWM",
      "price": 295.59,
      "chg_pct": 0.0,
      "open": 294.55,
      "high": 295.97,
      "low": 291.42,
      "volume": 32463155
    },
    {
      "ticker": "TLT",
      "price": 86.75,
      "chg_pct": 0.0,
      "open": 87.07,
      "high": 87.17,
      "low": 86.65,
      "volume": 32350902
    },
    {
      "ticker": "GLD",
      "price": 387.12,
      "chg_pct": 0.0,
      "open": 391.24,
      "high": 392.5,
      "low": 385.6,
      "volume": 7627319
    },
    {
      "ticker": "UUP",
      "price": 28.3,
      "chg_pct": 0.0,
      "open": 28.23,
      "high": 28.32,
      "low": 28.21,
      "volume": 2055269
    },
    {
      "ticker": "ASTS",
      "price": 80.66,
      "chg_pct": 0.0,
      "open": 85.3,
      "high": 85.7,
      "low": 77.12,
      "volume": 31679180
    },
    {
      "ticker": "RKLB",
      "price": 107.24,
      "chg_pct": 0.0,
      "open": 108.83,
      "high": 109.55,
      "low": 100.96,
      "volume": 70325989
    },
    {
      "ticker": "RDW",
      "price": 14.35,
      "chg_pct": 0.0,
      "open": 14.09,
      "high": 14.38,
      "low": 13.26,
      "volume": 46785421
    },
    {
      "ticker": "LUNR",
      "price": 22.85,
      "chg_pct": 0.0,
      "open": 22.74,
      "high": 22.9,
      "low": 21.21,
      "volume": 18739446
    }
  ],
  "market_signals": {
    "spy_chg": 0.0,
    "qqq_chg": 0.0,
    "iwm_chg": 0.0,
    "tlt_chg": 0.0,
    "gld_chg": 0.0,
    "uup_chg": 0.0,
    "defensive_avg": 0.0,
    "growth_avg": 0.0,
    "sentiment": "NEUTRAL",
    "sentiment_color": "#94a3b8"
  }
}