{"generated_at": "2026-07-20T20:37:34", "portfolio_updated_at": "2026-07-20T20:37:34", "source": "dataset_raw", "regime_short": "MILD RISK ON", "regime_score": "2", "regime_color": "#4ade80", "regime_emoji": "🟢", "cio_action": "SELECTIVE_BUY_RESEARCH_ONLY", "vix": "18.21", "vix_alert": false, "fg_score": 37.1, "fg_label": "FEAR", "fg_color": "#fbbf24", "market_val": 26202.45, "market_val_fmt": "$26,202.45", "total_pnl": -3799.34, "total_pnl_pct": -12.664, "pnl_fmt": "$-3,799.34 (-12.7%)", "pnl_color": "#ff5566", "cash": 24343.84, "cash_fmt": "$24,343.84", "cash_pct": 48.16, "cash_pct_fmt": "48.2%", "cash_color": "#4ade80", "integrity": "PASS", "integrity_color": "#4ade80", "positions": [{"ticker": "NEM", "qty": 60.0, "price": 90.0, "avg_price": 95.696, "avg_cost": 95.696, "chg_pct": 0.0, "market_val": 5400.0, "cost_basis": 5741.76, "unrealized": -341.73, "unrealized_p": -5.95, "pnl_integrity_status": "BROKER_REPORTED", "thesis": "GOLD"}, {"ticker": "AU", "qty": 64.0, "price": 75.52, "avg_price": 77.251, "avg_cost": 77.251, "chg_pct": 0.0, "market_val": 4833.28, "cost_basis": 4944.06, "unrealized": -110.76, "unrealized_p": -2.24, "pnl_integrity_status": "BROKER_REPORTED", "thesis": "GOLD"}, {"ticker": "AEM", "qty": 30.0, "price": 138.2, "avg_price": 160.438, "avg_cost": 160.438, "chg_pct": 0.0, "market_val": 4146.0, "cost_basis": 4813.14, "unrealized": -667.13, "unrealized_p": -13.86, "pnl_integrity_status": "BROKER_REPORTED", "thesis": "GOLD"}, {"ticker": "B", "qty": 110.0, "price": 35.0, "avg_price": 38.069, "avg_cost": 38.069, "chg_pct": 0.0, "market_val": 3850.0, "cost_basis": 4187.59, "unrealized": -337.63, "unrealized_p": -8.06, "pnl_integrity_status": "BROKER_REPORTED", "thesis": "GOLD"}, {"ticker": "QBTS", "qty": 200.0, "price": 17.1, "avg_price": 22.755, "avg_cost": 22.755, "chg_pct": 0.0, "market_val": 3420.32, "cost_basis": 4551.0, "unrealized": -1130.68, "unrealized_p": -24.84, "pnl_integrity_status": "BROKER_REPORTED", "thesis": "QUANTUM"}, {"ticker": "ARQQ", "qty": 100.0, "price": 17.5, "avg_price": 23.98, "avg_cost": 23.98, "chg_pct": 0.0, "market_val": 1750.0, "cost_basis": 2398.0, "unrealized": -648.0, "unrealized_p": -27.02, "pnl_integrity_status": "BROKER_REPORTED", "thesis": "WATCH"}, {"ticker": "IONQ", "qty": 40.0, "price": 35.81, "avg_price": 49.94, "avg_cost": 49.94, "chg_pct": 0.0, "market_val": 1432.28, "cost_basis": 1997.6, "unrealized": -565.32, "unrealized_p": -28.3, "pnl_integrity_status": "BROKER_REPORTED", "thesis": "QUANTUM"}, {"ticker": "QUBT", "qty": 100.0, "price": 7.92, "avg_price": 8.01, "avg_cost": 8.01, "chg_pct": 0.0, "market_val": 791.99, "cost_basis": 801.0, "unrealized": -9.01, "unrealized_p": -1.12, "pnl_integrity_status": "BROKER_REPORTED", "thesis": "QUANTUM"}, {"ticker": "VXX", "qty": 10.0, "price": 21.84, "avg_price": 21.195, "avg_cost": 21.195, "chg_pct": 0.0, "market_val": 218.4, "cost_basis": 211.95, "unrealized": 6.45, "unrealized_p": 3.04, "pnl_integrity_status": "BROKER_REPORTED", "thesis": "VOL_HEDGE"}, {"ticker": "VIXY", "qty": 10.0, "price": 21.08, "avg_price": 21.366, "avg_cost": 21.366, "chg_pct": 0.0, "market_val": 210.8, "cost_basis": 213.66, "unrealized": -2.86, "unrealized_p": -1.34, "pnl_integrity_status": "BROKER_REPORTED", "thesis": "VOL_HEDGE"}, {"ticker": "WFC", "qty": 1.0, "price": 87.89, "avg_price": 84.106, "avg_cost": 84.106, "chg_pct": 0.0, "market_val": 87.89, "cost_basis": 84.11, "unrealized": 3.79, "unrealized_p": 4.5, "pnl_integrity_status": "BROKER_REPORTED", "thesis": "BANKS"}, {"ticker": "BAC", "qty": 1.0, "price": 61.49, "avg_price": 57.953, "avg_cost": 57.953, "chg_pct": 0.0, "market_val": 61.49, "cost_basis": 57.95, "unrealized": 3.54, "unrealized_p": 6.1, "pnl_integrity_status": "BROKER_REPORTED", "thesis": "BANKS"}]}