{"generated_at": "2026-06-17T17:15:38", "regime_short": "NEUTRAL", "regime_score": "0", "regime_color": "#fbbf24", "regime_emoji": "🟡", "cio_action": "HOLD / WAIT", "vix": "16.37", "vix_alert": false, "fg_score": 39.5, "fg_label": "FEAR", "fg_color": "#fbbf24", "market_val": 3246.44, "market_val_fmt": "$3,246.44", "total_pnl": -23.35, "total_pnl_pct": -0.7, "pnl_fmt": "$-23.35 (-0.7%)", "pnl_color": "#ff5566", "cash": 54783.51, "cash_fmt": "$54,783.51", "cash_pct": 94.41, "cash_pct_fmt": "94.4%", "cash_color": "#4ade80", "integrity": "PASS", "integrity_color": "#4ade80", "positions": [{"ticker": "VXX", "qty": 50.0, "price": 22.45, "chg_pct": 0.0, "market_val": 1122.5, "unrealized": -9.6, "unrealized_p": -0.85, "pnl_integrity_status": "OK", "thesis": "WATCH"}, {"ticker": "VIXY", "qty": 50.0, "price": 21.65, "chg_pct": 0.0, "market_val": 1082.5, "unrealized": -11.52, "unrealized_p": -1.05, "pnl_integrity_status": "OK", "thesis": "WATCH"}, {"ticker": "ASTS", "qty": 3.0, "price": 85.9, "chg_pct": 0.0, "market_val": 257.7, "unrealized": 11.7, "unrealized_p": 4.76, "pnl_integrity_status": "OK", "thesis": "WATCH"}, {"ticker": "QBTS", "qty": 10.0, "price": 24.38, "chg_pct": 0.0, "market_val": 243.8, "unrealized": 59.32, "unrealized_p": 32.16, "pnl_integrity_status": "BROKER_PNL_SOURCE_CONFLICT", "thesis": "WATCH"}, {"ticker": "PL", "qty": 8.0, "price": 28.08, "chg_pct": 0.0, "market_val": 224.64, "unrealized": -13.76, "unrealized_p": -5.77, "pnl_integrity_status": "OK", "thesis": "WATCH"}, {"ticker": "LUNR", "qty": 9.0, "price": 23.6, "chg_pct": 0.0, "market_val": 212.4, "unrealized": -3.75, "unrealized_p": -1.74, "pnl_integrity_status": "BROKER_PNL_SOURCE_CONFLICT", "thesis": "WATCH"}, {"ticker": "QUBT", "qty": 10.0, "price": 10.29, "chg_pct": 0.0, "market_val": 102.9, "unrealized": -55.74, "unrealized_p": -35.14, "pnl_integrity_status": "BROKER_PNL_SOURCE_CONFLICT", "thesis": "WATCH"}]}