{
  "generated_at": "2026-06-18T05:22:41",
  "portfolio_updated_at": "2026-06-18T05:22:41",
  "source": "moomoo_direct",
  "regime_short": "MILD RISK OFF",
  "regime_score": "-2",
  "regime_color": "#ff5566",
  "regime_emoji": "🔴",
  "cio_action": "WAIT / HOLD",
  "vix": "18.43",
  "vix_alert": false,
  "fg_score": 32.7,
  "fg_label": "FEAR",
  "fg_color": "#fbbf24",
  "market_val": 3145.7,
  "market_val_fmt": "$3,145.70",
  "total_pnl": 49.63,
  "total_pnl_pct": 1.565,
  "pnl_fmt": "$49.63",
  "pnl_color": "#4ade80",
  "cash": 54956.12,
  "cash_fmt": "$54,956.12",
  "cash_pct": 94.59,
  "cash_pct_fmt": "94.6%",
  "cash_color": "#4ade80",
  "integrity": "PASS",
  "integrity_color": "#4ade80",
  "positions": [
    {
      "ticker": "VXX",
      "qty": 50.0,
      "price": 23.43,
      "chg_pct": null,
      "unrealized": 39.4,
      "unrealized_p": 3.48,
      "thesis": "WATCH"
    },
    {
      "ticker": "VIXY",
      "qty": 50.0,
      "price": 22.5,
      "chg_pct": null,
      "unrealized": 30.99,
      "unrealized_p": 2.83,
      "thesis": "WATCH"
    },
    {
      "ticker": "QUBT",
      "qty": 10.0,
      "price": 9.86,
      "chg_pct": null,
      "unrealized": -60.04,
      "unrealized_p": -37.85,
      "thesis": "WATCH"
    },
    {
      "ticker": "QBTS",
      "qty": 10.0,
      "price": 23.21,
      "chg_pct": null,
      "unrealized": 47.62,
      "unrealized_p": 25.81,
      "thesis": "WATCH"
    },
    {
      "ticker": "PL",
      "qty": 8.0,
      "price": 28.38,
      "chg_pct": null,
      "unrealized": -11.38,
      "unrealized_p": -4.77,
      "thesis": "WATCH"
    },
    {
      "ticker": "LUNR",
      "qty": 9.0,
      "price": 22.87,
      "chg_pct": null,
      "unrealized": -10.32,
      "unrealized_p": -4.78,
      "thesis": "WATCH"
    },
    {
      "ticker": "ASTS",
      "qty": 1.0,
      "price": 85.64,
      "chg_pct": null,
      "unrealized": 13.36,
      "unrealized_p": 18.48,
      "thesis": "WATCH"
    }
  ],
  "top_movers": [],
  "market_signals": {
    "spy_chg": null,
    "qqq_chg": null,
    "iwm_chg": null,
    "tlt_chg": null,
    "gld_chg": null,
    "uup_chg": null,
    "defensive_avg": null,
    "growth_avg": null,
    "sentiment": "INSUFFICIENT_DATA",
    "sentiment_color": "#94a3b8"
  }
}