{"generated_at": "2026-07-03 03:04 SGT", "probe_type": "thesis_evidence_v2", "live_regime": {"regime": "NEUTRAL", "regime_score": -1, "regime_short": "NEUTRAL (-1)", "regime_color": "#fbbf24", "regime_emoji": "🟡", "confidence": "MEDIUM_HIGH", "basis": "MKT -1.2% | VIX 16.6 | ECE 6/12 ON", "vix_level": 16.57, "spy_chg": -0.429, "qqq_chg": -1.972, "iwm_chg": -1.119, "ece_risk_on_n": 6, "ece_risk_off_n": 6, "ece_total_n": 12}, "gold_thesis": {"status": "CONFIRMING", "score": 0.938, "max_score": 1.0, "n_available": 8, "n_pass": 7, "n_watch": 1, "n_fail": 0, "n_missing": 0, "confidence": "HIGH", "critical_fail_count": 0, "core_action": "HOLD", "add_allowed": true, "gold_miner_cluster_pct": 0.0, "checks": {"gold_stabilizes_and_rises": {"status": "PASS", "score": 1.0, "evidence": "GLD +2.09%", "interpretation": "Gold flat/positive — thesis supportive.", "cio_implication": "Gold leg intact; monitor for continuation."}, "silver_confirms_or_gsr_compresses": {"status": "PASS", "score": 1.0, "evidence": "SLV +2.56% | GLD +2.09% | SLV-GLD +0.47% | GSR 6.89", "interpretation": "Silver outperforming gold — breadth confirming.", "cio_implication": "Precious metals broad confirmation; thesis strengthened."}, "miners_vs_gold": {"status": "PASS", "score": 1.0, "evidence": "GDX-GLD +1.56% | GDXJ-GLD +2.10%", "interpretation": "Miner ETFs confirming gold move — positive divergence.", "cio_implication": "Miner ETF leg confirming; thesis intact."}, "au_nem_vs_gdx": {"status": "PASS", "score": 1.0, "evidence": "AU-GDX +0.31% | NEM-GDX -0.12%", "interpretation": "Portfolio miners outperforming GDX — alpha captured.", "cio_implication": "Portfolio selection alpha confirmed; maintain HOLD."}, "real_yields_do_not_spike": {"status": "WATCH", "score": 0.5, "evidence": "TLT -0.06% | IEF +0.04%", "interpretation": "Mild bond weakness — modest yield pressure, manageable.", "cio_implication": "Gold can withstand mild yield rise."}, "dxy_does_not_surge": {"status": "PASS", "score": 1.0, "evidence": "UUP -0.57%", "interpretation": "Dollar flat/down — no USD headwind for gold.", "cio_implication": "USD not pressuring gold; favourable environment."}, "oil_risk_premium_elevated": {"status": "PASS", "score": 1.0, "evidence": "XLE +0.41% | Oil news hits: 3 | Oil falls to four-month low as US, Iran conclude talks in Do", "interpretation": "Oil-risk news active and energy price holding — premium intact.", "cio_implication": "Geopolitical oil-risk premium supports safe-haven gold thesis."}, "miners_not_liquidated_as_equity_beta": {"status": "PASS", "score": 1.0, "evidence": "GDX +3.65% | SPY -0.43% | GDX-SPY +4.08% | VXX -0.18%", "interpretation": "Miners holding up or outperforming equities — not sold as beta.", "cio_implication": "Miner/equity divergence positive; safe-haven function intact."}}, "key_metrics": {"gld_chg_pct": 2.09, "slv_chg_pct": 2.557, "gdx_chg_pct": 3.65, "gdxj_chg_pct": 4.192, "au_chg_pct": 3.962, "nem_chg_pct": 3.526, "uup_chg_pct": -0.574, "tlt_chg_pct": -0.064, "xle_chg_pct": 0.407, "spy_chg_pct": -0.429, "gsr_proxy": 6.89, "oil_news_count": 3, "gdx_vs_gld": 1.56, "gdx_vs_spy": 4.079}}, "event_correlations": [{"theme": "MAG7 / BIG TECH", "direction": "SELECTIVE_RISK_OFF", "basket_move": -1.267, "tickers": [{"t": "TSLA", "chg": -7.96, "px": 391.45}, {"t": "META", "chg": -4.71, "px": 584.04}, {"t": "AAPL", "chg": 4.57, "px": 307.84}, {"t": "NVDA", "chg": -2.19, "px": 193.25}, {"t": "MSFT", "chg": 1.67, "px": 390.68}, {"t": "GOOGL", "chg": -0.84, "px": 358.17}, {"t": "AMZN", "chg": 0.59, "px": 243.13}], "qualifying_rule": "3/7 pos · avg -1.27%", "tier": "T1:EARNINGS/MACRO", "n_pos": 3, "n_neg": 4, "n_avail": 7}, {"theme": "CONSUMER TECH / APPLE", "direction": "RISK_ON", "basket_move": 3.106, "tickers": [{"t": "NFLX", "chg": 5.18, "px": 78.03}, {"t": "AAPL", "chg": 4.57, "px": 307.84}, {"t": "SPOT", "chg": 3.12, "px": 487.23}, {"t": "SNAP", "chg": 2.0, "px": 4.84}, {"t": "PINS", "chg": 0.66, "px": 22.04}], "qualifying_rule": "5/5 pos · avg +3.11%", "tier": "T1:EARNINGS/MACRO", "n_pos": 5, "n_neg": 0, "n_avail": 5}, {"theme": "OIL / GAS", "direction": "RISK_ON", "basket_move": 0.836, "tickers": [{"t": "CVX", "chg": 1.57, "px": 168.28}, {"t": "OXY", "chg": 1.29, "px": 48.56}, {"t": "COP", "chg": 0.57, "px": 103.81}, {"t": "XLE", "chg": 0.41, "px": 53.02}, {"t": "XOM", "chg": 0.34, "px": 136.74}], "qualifying_rule": "5/5 pos · avg +0.84%", "tier": "T2:NEWS", "n_pos": 5, "n_neg": 0, "n_avail": 5}, {"theme": "QUANTUM", "direction": "RISK_OFF", "basket_move": -3.724, "tickers": [{"t": "IONQ", "chg": -5.41, "px": 48.62}, {"t": "RGTI", "chg": -4.95, "px": 17.75}, {"t": "QUBT", "chg": -4.51, "px": 9.01}, {"t": "QBTS", "chg": -4.17, "px": 22.52}, {"t": "IBM", "chg": 0.42, "px": 287.46}], "qualifying_rule": "1/5 pos · avg -3.72%", "tier": "T2:NEWS", "n_pos": 1, "n_neg": 4, "n_avail": 5}, {"theme": "AI / SEMIS", "direction": "RISK_OFF", "basket_move": -4.825, "tickers": [{"t": "AMAT", "chg": -8.59, "px": 595.0}, {"t": "ARM", "chg": -7.26, "px": 312.96}, {"t": "AMD", "chg": -5.22, "px": 512.63}, {"t": "SMCI", "chg": -2.86, "px": 26.86}, {"t": "AVGO", "chg": -2.83, "px": 358.9}, {"t": "NVDA", "chg": -2.19, "px": 193.25}], "qualifying_rule": "0/6 pos · avg -4.83%", "tier": "T2:NEWS", "n_pos": 0, "n_neg": 6, "n_avail": 6}, {"theme": "CLEAN ENERGY / SOLAR", "direction": "RISK_OFF", "basket_move": -4.546, "tickers": [{"t": "ENPH", "chg": -8.54, "px": 42.84}, {"t": "SEDG", "chg": -5.75, "px": 52.78}, {"t": "FSLR", "chg": -4.21, "px": 222.3}, {"t": "RUN", "chg": -3.47, "px": 12.65}, {"t": "PLUG", "chg": -0.76, "px": 2.62}], "qualifying_rule": "0/5 pos · avg -4.55%", "tier": "T2:NEWS", "n_pos": 0, "n_neg": 5, "n_avail": 5}, {"theme": "SPACE / DEFENSE", "direction": "RISK_OFF", "basket_move": -0.903, "tickers": [{"t": "LUNR", "chg": -4.13, "px": 19.36}, {"t": "ASTS", "chg": -4.1, "px": 82.57}, {"t": "LMT", "chg": 3.64, "px": 540.84}, {"t": "RTX", "chg": 3.45, "px": 198.4}, {"t": "SPCE", "chg": -2.16, "px": 2.72}, {"t": "PL", "chg": -2.04, "px": 30.96}, {"t": "RKLB", "chg": -0.98, "px": 99.09}], "qualifying_rule": "2/7 pos · avg -0.90%", "tier": "T1:EARNINGS/MACRO", "n_pos": 2, "n_neg": 5, "n_avail": 7}, {"theme": "MACRO / FED", "direction": "RISK_OFF", "basket_move": -1.173, "tickers": [{"t": "QQQ", "chg": -1.97, "px": 710.87}, {"t": "IWM", "chg": -1.12, "px": 295.97}, {"t": "SPY", "chg": -0.43, "px": 742.56}], "qualifying_rule": "0/3 pos · avg -1.17%", "tier": "T1:EARNINGS/MACRO", "n_pos": 0, "n_neg": 3, "n_avail": 3}, {"theme": "GOLD / SAFE HAVEN", "direction": "RISK_ON", "basket_move": 3.33, "tickers": [{"t": "GDXJ", "chg": 4.19, "px": 102.16}, {"t": "AU", "chg": 3.96, "px": 84.09}, {"t": "GDX", "chg": 3.65, "px": 77.81}, {"t": "NEM", "chg": 3.53, "px": 96.59}, {"t": "SLV", "chg": 2.56, "px": 54.95}, {"t": "GLD", "chg": 2.09, "px": 378.34}], "qualifying_rule": "6/6 pos · avg +3.33%", "tier": "T2:NEWS", "n_pos": 6, "n_neg": 0, "n_avail": 6}, {"theme": "SOFTWARE / CYBER", "direction": "RISK_ON", "basket_move": 0.598, "tickers": [{"t": "CRWD", "chg": 1.76, "px": 196.59}, {"t": "ZS", "chg": 1.02, "px": 147.94}, {"t": "OKTA", "chg": 0.7, "px": 141.44}, {"t": "FTNT", "chg": -0.55, "px": 158.11}, {"t": "PANW", "chg": 0.06, "px": 352.25}], "qualifying_rule": "4/5 pos · avg +0.60%", "tier": "T2:NEWS", "n_pos": 4, "n_neg": 1, "n_avail": 5}, {"theme": "BANKS / LIQUIDITY", "direction": "SELECTIVE_RISK_ON", "basket_move": 0.434, "tickers": [{"t": "XLF", "chg": 1.18, "px": 55.42}, {"t": "MS", "chg": 0.75, "px": 213.46}, {"t": "BAC", "chg": 0.36, "px": 58.57}, {"t": "GS", "chg": -0.07, "px": 1018.92}, {"t": "JPM", "chg": -0.05, "px": 333.92}], "qualifying_rule": "3/5 pos · avg +0.43%", "tier": "T2:NEWS", "n_pos": 3, "n_neg": 2, "n_avail": 5}, {"theme": "EARNINGS CATALYST", "direction": "SELECTIVE_RISK_ON", "basket_move": 1.603, "tickers": [{"t": "ACN", "chg": 5.12, "px": 137.84}, {"t": "ADBE", "chg": 4.76, "px": 221.01}, {"t": "COST", "chg": 2.58, "px": 948.48}, {"t": "NKE", "chg": 1.52, "px": 43.72}, {"t": "ORCL", "chg": -1.29, "px": 140.66}, {"t": "DAL", "chg": -0.74, "px": 92.37}, {"t": "FDX", "chg": -0.73, "px": 311.61}], "qualifying_rule": "4/7 pos · avg +1.60%", "tier": "T1:EARNINGS/MACRO", "n_pos": 4, "n_neg": 3, "n_avail": 7}], "correlations_as_of": "2026-07-03 03:04 SGT", "top_movers": [{"ticker": "AMAT", "chg_pct": -8.59, "price": 595.0}, {"ticker": "ENPH", "chg_pct": -8.54, "price": 42.84}, {"ticker": "TSLA", "chg_pct": -7.959, "price": 391.45}, {"ticker": "ARM", "chg_pct": -7.261, "price": 312.965}, {"ticker": "SEDG", "chg_pct": -5.75, "price": 52.78}, {"ticker": "IONQ", "chg_pct": -5.412, "price": 48.618}, {"ticker": "AMD", "chg_pct": -5.222, "price": 512.635}, {"ticker": "NFLX", "chg_pct": 5.183, "price": 78.035}, {"ticker": "ACN", "chg_pct": 5.117, "price": 137.84}, {"ticker": "RGTI", "chg_pct": -4.952, "price": 17.755}, {"ticker": "ADBE", "chg_pct": 4.756, "price": 221.015}, {"ticker": "META", "chg_pct": -4.71, "price": 584.04}, {"ticker": "AAPL", "chg_pct": 4.572, "price": 307.84}, {"ticker": "QUBT", "chg_pct": -4.507, "price": 9.005}, {"ticker": "FSLR", "chg_pct": -4.214, "price": 222.3}], "market_signals": {"spy_chg": -0.429, "qqq_chg": -1.972, "gld_chg": 2.09, "tlt_chg": -0.064}}