{"generated_at": "2026-07-01 02:47 SGT", "probe_type": "thesis_evidence_v2", "live_regime": {"regime": "MILD RISK ON", "regime_score": 3, "regime_short": "MILD RISK ON (+3)", "regime_color": "#86efac", "regime_emoji": "🟢", "confidence": "MEDIUM_HIGH", "basis": "MKT +1.0% | VIX 16.6 | ECE 6/12 ON", "vix_level": 16.64, "spy_chg": 0.792, "qqq_chg": 1.7, "iwm_chg": 0.508, "ece_risk_on_n": 6, "ece_risk_off_n": 5, "ece_total_n": 12}, "gold_thesis": {"status": "CONFIRMING", "score": 0.75, "max_score": 1.0, "n_available": 8, "n_pass": 4, "n_watch": 4, "n_fail": 0, "n_missing": 0, "confidence": "HIGH", "critical_fail_count": 0, "core_action": "HOLD", "add_allowed": true, "gold_miner_cluster_pct": 0.0, "checks": {"gold_stabilizes_and_rises": {"status": "PASS", "score": 1.0, "evidence": "GLD +0.32%", "interpretation": "Gold flat/positive — thesis supportive.", "cio_implication": "Gold leg intact; monitor for continuation."}, "silver_confirms_or_gsr_compresses": {"status": "PASS", "score": 1.0, "evidence": "SLV +2.55% | GLD +0.32% | SLV-GLD +2.24% | GSR 6.84", "interpretation": "Silver outperforming gold — breadth confirming.", "cio_implication": "Precious metals broad confirmation; thesis strengthened."}, "miners_vs_gold": {"status": "WATCH", "score": 0.5, "evidence": "GDX-GLD -0.67% | GDXJ-GLD -0.82%", "interpretation": "Miners slightly behind gold — minor drag.", "cio_implication": "Acceptable underperformance; monitor."}, "au_nem_vs_gdx": {"status": "WATCH", "score": 0.5, "evidence": "AU-GDX -0.52% | NEM-GDX -0.64%", "interpretation": "Portfolio miners slightly lagging GDX — marginal.", "cio_implication": "Monitor relative performance; no immediate action."}, "real_yields_do_not_spike": {"status": "WATCH", "score": 0.5, "evidence": "TLT -0.79% | IEF -0.35%", "interpretation": "Mild bond weakness — modest yield pressure, manageable.", "cio_implication": "Gold can withstand mild yield rise."}, "dxy_does_not_surge": {"status": "PASS", "score": 1.0, "evidence": "UUP +0.14%", "interpretation": "Dollar flat/down — no USD headwind for gold.", "cio_implication": "USD not pressuring gold; favourable environment."}, "oil_risk_premium_elevated": {"status": "PASS", "score": 1.0, "evidence": "XLE -0.38% | Oil news hits: 4 | Asia's crude oil imports tick up in June but uncertainty rei", "interpretation": "Oil-risk news active and energy price holding — premium intact.", "cio_implication": "Geopolitical oil-risk premium supports safe-haven gold thesis."}, "miners_not_liquidated_as_equity_beta": {"status": "WATCH", "score": 0.5, "evidence": "GDX -0.36% | SPY +0.79% | GDX-SPY -1.15% | VXX -1.62%", "interpretation": "Miners slightly lagging equities — within tolerable range.", "cio_implication": "Watch for further divergence; not yet liquidation."}}, "key_metrics": {"gld_chg_pct": 0.317, "slv_chg_pct": 2.553, "gdx_chg_pct": -0.357, "gdxj_chg_pct": -0.505, "au_chg_pct": -0.874, "nem_chg_pct": -0.995, "uup_chg_pct": 0.141, "tlt_chg_pct": -0.794, "xle_chg_pct": -0.383, "spy_chg_pct": 0.792, "gsr_proxy": 6.84, "oil_news_count": 4, "gdx_vs_gld": -0.674, "gdx_vs_spy": -1.149}}, "event_correlations": [{"theme": "MAG7 / BIG TECH", "direction": "RISK_ON", "basket_move": 0.736, "tickers": [{"t": "AAPL", "chg": 1.93, "px": 287.18}, {"t": "TSLA", "chg": 1.88, "px": 419.59}, {"t": "NVDA", "chg": 1.85, "px": 198.59}, {"t": "AMZN", "chg": -0.98, "px": 237.78}, {"t": "GOOGL", "chg": 0.68, "px": 356.07}, {"t": "META", "chg": -0.59, "px": 559.29}, {"t": "MSFT", "chg": 0.38, "px": 369.98}], "qualifying_rule": "5/7 pos · avg +0.74%", "tier": "T1:EARNINGS/MACRO", "n_pos": 5, "n_neg": 2, "n_avail": 7}, {"theme": "CONSUMER TECH / APPLE", "direction": "RISK_OFF", "basket_move": -0.81, "tickers": [{"t": "PINS", "chg": -4.27, "px": 20.95}, {"t": "NFLX", "chg": -2.05, "px": 72.27}, {"t": "AAPL", "chg": 1.93, "px": 287.18}, {"t": "SNAP", "chg": 0.34, "px": 4.43}, {"t": "SPOT", "chg": 0.0, "px": 462.3}], "qualifying_rule": "2/5 pos · avg -0.81%", "tier": "T1:EARNINGS/MACRO", "n_pos": 2, "n_neg": 2, "n_avail": 5}, {"theme": "OIL / GAS", "direction": "SELECTIVE_RISK_OFF", "basket_move": -0.278, "tickers": [{"t": "CVX", "chg": -0.98, "px": 166.82}, {"t": "OXY", "chg": -0.47, "px": 48.86}, {"t": "XLE", "chg": -0.38, "px": 53.38}, {"t": "XOM", "chg": 0.34, "px": 136.52}, {"t": "COP", "chg": 0.1, "px": 104.3}], "qualifying_rule": "2/5 pos · avg -0.28%", "tier": "T2:NEWS", "n_pos": 2, "n_neg": 3, "n_avail": 5}, {"theme": "QUANTUM", "direction": "RISK_OFF", "basket_move": -0.916, "tickers": [{"t": "QUBT", "chg": -2.77, "px": 9.64}, {"t": "IONQ", "chg": -1.8, "px": 52.91}, {"t": "IBM", "chg": 1.21, "px": 281.35}, {"t": "RGTI", "chg": -1.05, "px": 19.23}, {"t": "QBTS", "chg": -0.17, "px": 23.79}], "qualifying_rule": "1/5 pos · avg -0.92%", "tier": "T2:NEWS", "n_pos": 1, "n_neg": 4, "n_avail": 5}, {"theme": "AI / SEMIS", "direction": "RISK_ON", "basket_move": 4.57, "tickers": [{"t": "AMD", "chg": 8.05, "px": 582.92}, {"t": "AMAT", "chg": 6.21, "px": 737.75}, {"t": "SMCI", "chg": 5.35, "px": 29.66}, {"t": "ARM", "chg": 4.47, "px": 358.95}, {"t": "NVDA", "chg": 1.85, "px": 198.59}, {"t": "AVGO", "chg": 1.49, "px": 377.99}], "qualifying_rule": "6/6 pos · avg +4.57%", "tier": "T2:NEWS", "n_pos": 6, "n_neg": 0, "n_avail": 6}, {"theme": "CLEAN ENERGY / SOLAR", "direction": "RISK_ON", "basket_move": 2.684, "tickers": [{"t": "SEDG", "chg": 6.08, "px": 58.73}, {"t": "PLUG", "chg": 4.83, "px": 2.71}, {"t": "ENPH", "chg": 2.19, "px": 49.4}, {"t": "FSLR", "chg": 1.02, "px": 235.18}, {"t": "RUN", "chg": -0.7, "px": 13.38}], "qualifying_rule": "4/5 pos · avg +2.68%", "tier": "T2:NEWS", "n_pos": 4, "n_neg": 1, "n_avail": 5}, {"theme": "SPACE / DEFENSE", "direction": "RISK_ON", "basket_move": 1.759, "tickers": [{"t": "PL", "chg": 7.13, "px": 33.51}, {"t": "RKLB", "chg": 3.17, "px": 101.11}, {"t": "SPCE", "chg": -2.89, "px": 2.85}, {"t": "ASTS", "chg": 1.66, "px": 88.21}, {"t": "LUNR", "chg": 1.19, "px": 21.22}, {"t": "RTX", "chg": 1.05, "px": 189.29}, {"t": "LMT", "chg": 1.0, "px": 507.1}], "qualifying_rule": "6/7 pos · avg +1.76%", "tier": "T1:EARNINGS/MACRO", "n_pos": 6, "n_neg": 1, "n_avail": 7}, {"theme": "MACRO / FED", "direction": "RISK_ON", "basket_move": 1.0, "tickers": [{"t": "QQQ", "chg": 1.7, "px": 736.39}, {"t": "SPY", "chg": 0.79, "px": 746.87}, {"t": "IWM", "chg": 0.51, "px": 300.49}], "qualifying_rule": "3/3 pos · avg +1.00%", "tier": "T1:EARNINGS/MACRO", "n_pos": 3, "n_neg": 0, "n_avail": 3}, {"theme": "GOLD / SAFE HAVEN", "direction": "NEUTRAL", "basket_move": 0.023, "tickers": [{"t": "SLV", "chg": 2.55, "px": 54.02}, {"t": "NEM", "chg": -0.99, "px": 93.57}, {"t": "AU", "chg": -0.87, "px": 81.08}, {"t": "GDXJ", "chg": -0.51, "px": 98.42}, {"t": "GDX", "chg": -0.36, "px": 75.41}, {"t": "GLD", "chg": 0.32, "px": 369.75}], "qualifying_rule": "2/6 pos · avg +0.02%", "tier": "T2:NEWS", "n_pos": 2, "n_neg": 4, "n_avail": 6}, {"theme": "SOFTWARE / CYBER", "direction": "RISK_ON", "basket_move": 1.858, "tickers": [{"t": "OKTA", "chg": 3.14, "px": 135.44}, {"t": "CRWD", "chg": 2.77, "px": 763.52}, {"t": "PANW", "chg": 2.58, "px": 340.56}, {"t": "ZS", "chg": 2.13, "px": 140.53}, {"t": "FTNT", "chg": -1.33, "px": 153.34}], "qualifying_rule": "4/5 pos · avg +1.86%", "tier": "T2:NEWS", "n_pos": 4, "n_neg": 1, "n_avail": 5}, {"theme": "BANKS / LIQUIDITY", "direction": "RISK_OFF", "basket_move": -0.68, "tickers": [{"t": "BAC", "chg": -1.4, "px": 57.07}, {"t": "MS", "chg": -0.78, "px": 210.06}, {"t": "GS", "chg": -0.72, "px": 1012.87}, {"t": "JPM", "chg": -0.43, "px": 327.98}, {"t": "XLF", "chg": -0.07, "px": 53.68}], "qualifying_rule": "0/5 pos · avg -0.68%", "tier": "T2:NEWS", "n_pos": 0, "n_neg": 5, "n_avail": 5}, {"theme": "EARNINGS CATALYST", "direction": "RISK_OFF", "basket_move": -0.854, "tickers": [{"t": "FDX", "chg": -4.16, "px": 311.87}, {"t": "COST", "chg": -0.9, "px": 938.21}, {"t": "ADBE", "chg": -0.82, "px": 204.73}, {"t": "DAL", "chg": 0.69, "px": 93.81}, {"t": "ORCL", "chg": -0.48, "px": 147.05}, {"t": "ACN", "chg": -0.2, "px": 124.48}, {"t": "NKE", "chg": -0.11, "px": 41.44}], "qualifying_rule": "1/7 pos · avg -0.85%", "tier": "T1:EARNINGS/MACRO", "n_pos": 1, "n_neg": 6, "n_avail": 7}], "correlations_as_of": "2026-07-01 02:47 SGT", "top_movers": [{"ticker": "AMD", "chg_pct": 8.05, "price": 582.92}, {"ticker": "PL", "chg_pct": 7.129, "price": 33.5101}, {"ticker": "AMAT", "chg_pct": 6.205, "price": 737.745}, {"ticker": "SEDG", "chg_pct": 6.078, "price": 58.725}, {"ticker": "^VIX", "chg_pct": -5.722, "price": 16.64}, {"ticker": "SMCI", "chg_pct": 5.346, "price": 29.655}, {"ticker": "PLUG", "chg_pct": 4.826, "price": 2.715}, {"ticker": "ARM", "chg_pct": 4.475, "price": 358.955}, {"ticker": "PINS", "chg_pct": -4.273, "price": 20.945}, {"ticker": "FDX", "chg_pct": -4.158, "price": 311.87}, {"ticker": "RKLB", "chg_pct": 3.168, "price": 101.115}, {"ticker": "OKTA", "chg_pct": 3.141, "price": 135.435}, {"ticker": "SPCE", "chg_pct": -2.891, "price": 2.855}, {"ticker": "CRWD", "chg_pct": 2.774, "price": 763.5201}, {"ticker": "QUBT", "chg_pct": -2.772, "price": 9.645}], "market_signals": {"spy_chg": 0.792, "qqq_chg": 1.7, "gld_chg": 0.317, "tlt_chg": -0.794}}