{"generated_at": "2026-07-18 02:48 SGT", "probe_type": "thesis_evidence_v2", "live_regime": {"regime": "NEUTRAL", "regime_score": -1, "regime_short": "NEUTRAL (-1)", "regime_color": "#fbbf24", "regime_emoji": "🟡", "confidence": "MEDIUM_HIGH", "basis": "MKT -0.9% | VIX 18.7 | ECE 5/12 ON", "vix_level": 18.67, "spy_chg": -0.884, "qqq_chg": -1.183, "iwm_chg": -0.591, "ece_risk_on_n": 5, "ece_risk_off_n": 6, "ece_total_n": 12}, "gold_thesis": {"status": "CONFIRMING", "score": 0.812, "max_score": 1.0, "n_available": 8, "n_pass": 6, "n_watch": 1, "n_fail": 1, "n_missing": 0, "confidence": "MEDIUM", "critical_fail_count": 1, "core_action": "HOLD", "add_allowed": true, "gold_miner_cluster_pct": 0.0, "checks": {"gold_stabilizes_and_rises": {"status": "PASS", "score": 1.0, "evidence": "GLD +0.76%", "interpretation": "Gold flat/positive — thesis supportive.", "cio_implication": "Gold leg intact; monitor for continuation."}, "silver_confirms_or_gsr_compresses": {"status": "WATCH", "score": 0.5, "evidence": "SLV +0.57% | GLD +0.76% | SLV-GLD -0.19% | GSR 7.26", "interpretation": "Silver tracking gold — neutral breadth.", "cio_implication": "Silver not diverging; wait for confirmation direction."}, "miners_vs_gold": {"status": "FAIL", "score": 0.0, "evidence": "GDX-GLD -1.17% | GDXJ-GLD -1.30%", "interpretation": "Miners materially underperforming gold — negative divergence.", "cio_implication": "Miner ETF rejection; consider whether gold move is credible for equity miners."}, "au_nem_vs_gdx": {"status": "PASS", "score": 1.0, "evidence": "AU-GDX +1.23% | NEM-GDX -0.74%", "interpretation": "Portfolio miners outperforming GDX — alpha captured.", "cio_implication": "Portfolio selection alpha confirmed; maintain HOLD."}, "real_yields_do_not_spike": {"status": "PASS", "score": 1.0, "evidence": "TLT +0.46% | IEF +0.19%", "interpretation": "Bonds flat/up — no yield spike; gold supportive.", "cio_implication": "Rate environment not hostile to gold."}, "dxy_does_not_surge": {"status": "PASS", "score": 1.0, "evidence": "UUP +0.02%", "interpretation": "Dollar flat/down — no USD headwind for gold.", "cio_implication": "USD not pressuring gold; favourable environment."}, "oil_risk_premium_elevated": {"status": "PASS", "score": 1.0, "evidence": "XLE +0.91% | Oil news hits: 4 | China's oil imports have plunged during the Iran war. How mu", "interpretation": "Oil-risk news active and energy price holding — premium intact.", "cio_implication": "Geopolitical oil-risk premium supports safe-haven gold thesis."}, "miners_not_liquidated_as_equity_beta": {"status": "PASS", "score": 1.0, "evidence": "GDX -0.41% | SPY -0.88% | GDX-SPY +0.48% | VXX +4.31%", "interpretation": "Miners holding up or outperforming equities — not sold as beta.", "cio_implication": "Miner/equity divergence positive; safe-haven function intact."}}, "key_metrics": {"gld_chg_pct": 0.76, "slv_chg_pct": 0.566, "gdx_chg_pct": -0.406, "gdxj_chg_pct": -0.54, "au_chg_pct": 0.825, "nem_chg_pct": -1.15, "uup_chg_pct": 0.018, "tlt_chg_pct": 0.457, "xle_chg_pct": 0.912, "spy_chg_pct": -0.884, "gsr_proxy": 7.26, "oil_news_count": 4, "gdx_vs_gld": -1.166, "gdx_vs_spy": 0.478}}, "event_correlations": [{"theme": "MAG7 / BIG TECH", "direction": "RISK_OFF", "basket_move": -1.7, "tickers": [{"t": "GOOGL", "chg": -2.73, "px": 344.78}, {"t": "META", "chg": -2.65, "px": 646.96}, {"t": "TSLA", "chg": -2.45, "px": 381.47}, {"t": "NVDA", "chg": -1.92, "px": 203.42}, {"t": "MSFT", "chg": -1.59, "px": 394.73}, {"t": "AMZN", "chg": -0.94, "px": 247.53}, {"t": "AAPL", "chg": 0.38, "px": 334.53}], "qualifying_rule": "1/7 pos · avg -1.70%", "tier": "T1:EARNINGS/MACRO", "n_pos": 1, "n_neg": 6, "n_avail": 7}, {"theme": "CONSUMER TECH / APPLE", "direction": "RISK_OFF", "basket_move": -2.408, "tickers": [{"t": "NFLX", "chg": -7.22, "px": 68.98}, {"t": "SNAP", "chg": -3.31, "px": 4.54}, {"t": "PINS", "chg": -1.28, "px": 22.8}, {"t": "SPOT", "chg": -0.61, "px": 473.18}, {"t": "AAPL", "chg": 0.38, "px": 334.53}], "qualifying_rule": "1/5 pos · avg -2.41%", "tier": "T1:EARNINGS/MACRO", "n_pos": 1, "n_neg": 4, "n_avail": 5}, {"theme": "OIL / GAS", "direction": "RISK_ON", "basket_move": 1.398, "tickers": [{"t": "OXY", "chg": 2.04, "px": 54.74}, {"t": "CVX", "chg": 1.54, "px": 186.69}, {"t": "XOM", "chg": 1.26, "px": 147.79}, {"t": "COP", "chg": 1.24, "px": 114.23}, {"t": "XLE", "chg": 0.91, "px": 57.54}], "qualifying_rule": "5/5 pos · avg +1.40%", "tier": "T2:NEWS", "n_pos": 5, "n_neg": 0, "n_avail": 5}, {"theme": "QUANTUM", "direction": "SELECTIVE_RISK_ON", "basket_move": 0.232, "tickers": [{"t": "IBM", "chg": -3.37, "px": 211.68}, {"t": "QUBT", "chg": 3.01, "px": 7.87}, {"t": "RGTI", "chg": 1.14, "px": 14.26}, {"t": "QBTS", "chg": 0.58, "px": 17.02}, {"t": "IONQ", "chg": -0.2, "px": 35.03}], "qualifying_rule": "3/5 pos · avg +0.23%", "tier": "T2:NEWS", "n_pos": 3, "n_neg": 2, "n_avail": 5}, {"theme": "AI / SEMIS", "direction": "RISK_OFF", "basket_move": -1.025, "tickers": [{"t": "AMAT", "chg": -5.03, "px": 532.75}, {"t": "ARM", "chg": 2.2, "px": 267.77}, {"t": "NVDA", "chg": -1.92, "px": 203.42}, {"t": "AMD", "chg": -0.71, "px": 497.38}, {"t": "SMCI", "chg": -0.39, "px": 24.59}, {"t": "AVGO", "chg": -0.3, "px": 373.32}], "qualifying_rule": "1/6 pos · avg -1.02%", "tier": "T2:NEWS", "n_pos": 1, "n_neg": 5, "n_avail": 6}, {"theme": "CLEAN ENERGY / SOLAR", "direction": "RISK_ON", "basket_move": 0.746, "tickers": [{"t": "PLUG", "chg": 1.86, "px": 2.19}, {"t": "ENPH", "chg": 1.45, "px": 41.67}, {"t": "SEDG", "chg": 1.36, "px": 53.05}, {"t": "RUN", "chg": -1.24, "px": 11.99}, {"t": "FSLR", "chg": 0.3, "px": 212.56}], "qualifying_rule": "4/5 pos · avg +0.75%", "tier": "T2:NEWS", "n_pos": 4, "n_neg": 1, "n_avail": 5}, {"theme": "SPACE / DEFENSE", "direction": "SELECTIVE_RISK_ON", "basket_move": 1.621, "tickers": [{"t": "ASTS", "chg": 6.94, "px": 58.83}, {"t": "PL", "chg": 3.58, "px": 22.88}, {"t": "SPCE", "chg": -1.74, "px": 2.54}, {"t": "LUNR", "chg": 1.71, "px": 13.67}, {"t": "RKLB", "chg": 1.63, "px": 68.45}, {"t": "LMT", "chg": -0.72, "px": 509.81}, {"t": "RTX", "chg": -0.05, "px": 194.26}], "qualifying_rule": "4/7 pos · avg +1.62%", "tier": "T1:EARNINGS/MACRO", "n_pos": 4, "n_neg": 3, "n_avail": 7}, {"theme": "MACRO / FED", "direction": "RISK_OFF", "basket_move": -0.883, "tickers": [{"t": "QQQ", "chg": -1.18, "px": 697.59}, {"t": "SPY", "chg": -0.88, "px": 744.08}, {"t": "IWM", "chg": -0.59, "px": 293.84}], "qualifying_rule": "0/3 pos · avg -0.88%", "tier": "T1:EARNINGS/MACRO", "n_pos": 0, "n_neg": 3, "n_avail": 3}, {"theme": "GOLD / SAFE HAVEN", "direction": "NEUTRAL", "basket_move": 0.008, "tickers": [{"t": "NEM", "chg": -1.15, "px": 89.78}, {"t": "AU", "chg": 0.82, "px": 76.98}, {"t": "GLD", "chg": 0.76, "px": 367.74}, {"t": "SLV", "chg": 0.57, "px": 50.67}, {"t": "GDXJ", "chg": -0.54, "px": 92.15}, {"t": "GDX", "chg": -0.41, "px": 71.11}], "qualifying_rule": "3/6 pos · avg +0.01%", "tier": "T2:NEWS", "n_pos": 3, "n_neg": 3, "n_avail": 6}, {"theme": "SOFTWARE / CYBER", "direction": "RISK_ON", "basket_move": 1.028, "tickers": [{"t": "ZS", "chg": 2.08, "px": 149.47}, {"t": "FTNT", "chg": 1.06, "px": 162.48}, {"t": "PANW", "chg": 0.91, "px": 357.23}, {"t": "OKTA", "chg": 0.89, "px": 149.06}, {"t": "CRWD", "chg": 0.2, "px": 204.17}], "qualifying_rule": "5/5 pos · avg +1.03%", "tier": "T2:NEWS", "n_pos": 5, "n_neg": 0, "n_avail": 5}, {"theme": "BANKS / LIQUIDITY", "direction": "RISK_OFF", "basket_move": -1.02, "tickers": [{"t": "GS", "chg": -2.17, "px": 1071.74}, {"t": "MS", "chg": -1.4, "px": 215.31}, {"t": "XLF", "chg": -0.85, "px": 56.27}, {"t": "BAC", "chg": -0.51, "px": 61.17}, {"t": "JPM", "chg": -0.17, "px": 342.56}], "qualifying_rule": "0/5 pos · avg -1.02%", "tier": "T2:NEWS", "n_pos": 0, "n_neg": 5, "n_avail": 5}, {"theme": "EARNINGS CATALYST", "direction": "RISK_OFF", "basket_move": -0.616, "tickers": [{"t": "DAL", "chg": -2.65, "px": 84.41}, {"t": "NKE", "chg": -2.03, "px": 43.66}, {"t": "ORCL", "chg": 1.72, "px": 126.34}, {"t": "FDX", "chg": -1.37, "px": 313.84}, {"t": "ADBE", "chg": 1.22, "px": 238.17}, {"t": "COST", "chg": -0.7, "px": 938.9}, {"t": "ACN", "chg": -0.5, "px": 143.89}], "qualifying_rule": "2/7 pos · avg -0.62%", "tier": "T1:EARNINGS/MACRO", "n_pos": 2, "n_neg": 5, "n_avail": 7}], "correlations_as_of": "2026-07-18 02:48 SGT", "top_movers": [{"ticker": "^VIX", "chg_pct": 11.596, "price": 18.67}, {"ticker": "UVXY", "chg_pct": 7.87, "price": 25.22}, {"ticker": "NFLX", "chg_pct": -7.216, "price": 68.985}, {"ticker": "ASTS", "chg_pct": 6.944, "price": 58.83}, {"ticker": "AMAT", "chg_pct": -5.025, "price": 532.745}, {"ticker": "VXX", "chg_pct": 4.312, "price": 22.375}, {"ticker": "PL", "chg_pct": 3.576, "price": 22.88}, {"ticker": "IBM", "chg_pct": -3.365, "price": 211.68}, {"ticker": "SNAP", "chg_pct": -3.305, "price": 4.535}, {"ticker": "QUBT", "chg_pct": 3.01, "price": 7.87}, {"ticker": "GOOGL", "chg_pct": -2.731, "price": 344.78}, {"ticker": "DAL", "chg_pct": -2.647, "price": 84.405}, {"ticker": "META", "chg_pct": -2.645, "price": 646.96}, {"ticker": "TSLA", "chg_pct": -2.452, "price": 381.47}, {"ticker": "ARM", "chg_pct": 2.198, "price": 267.77}], "market_signals": {"spy_chg": -0.884, "qqq_chg": -1.183, "gld_chg": 0.76, "tlt_chg": 0.457}}