{"thesis_id": "THESIS-HAWKISH-WARSH-FED", "generated_at": "2026-07-07 22:52 SGT", "status": "WARNING", "score": 42.5, "fed_tone": {"status": "UNKNOWN", "score": 10.0, "hawkish_count": 0, "dovish_count": 0, "evidence": ["No Fed/macro keywords found in recent headlines — neutral assumed"]}, "rates_confirmation": {"status": "WATCH", "score": 9.5, "tlt_change_pct": -0.561, "ief_change_pct": -0.239, "shy_change_pct": -0.039, "us_10y_proxy": 0.01, "us_30y_proxy": 0.01, "us_10y_level": 4.49, "us_30y_level": 4.98, "yield_snapshot_date": "2026-07-07", "yield_previous_snapshot_date": "2026-07-06", "yield_delta_source": "FRED_DB_HISTORY", "evidence": ["TLT -0.6% (rate pressure active)", "FRED levels: 10Y 4.49%, 30Y 4.98%"]}, "dollar_confirmation": {"status": "WATCH", "score": 5.0, "uup_change_pct": 0.088, "evidence": []}, "bank_confirmation": {"status": "WATCH", "score": 8.5, "xlf_change_pct": 0.356, "jpm_change_pct": 0.367, "bac_change_pct": 0.434, "wfc_change_pct": -0.051, "gs_change_pct": -1.49, "ms_change_pct": -0.545, "credit_stress": false, "hyg_change_pct": -0.106, "jnk_change_pct": -0.099, "evidence": []}, "gold_miner_confirmation": {"status": "FAIL", "score": 1.5, "gld_change_pct": -0.179, "slv_change_pct": -1.643, "gdx_change_pct": -3.01, "gdxj_change_pct": -3.782, "au_change_pct": -2.296, "nem_change_pct": -3.241, "gdx_vs_gld_spread": -2.831, "evidence": ["GDX -3.0% (miners breaking down)", "AU/NEM avg -2.8% (portfolio miners weak)"]}, "high_beta_risk": {"status": "WATCH", "score": 3.0, "qqq_change_pct": -2.196, "iwm_change_pct": -0.831, "vxx_change_pct": 1.605, "uvxy_change_pct": 2.438, "nvda_change_pct": -1.795, "red_flag": false, "evidence": ["QQQ -2.2% (tech selling under hawkish)"]}, "credit_stress": {"status": "WATCH", "score": 5.0, "hyg_change_pct": -0.106, "jnk_change_pct": -0.099, "lqd_change_pct": -0.469, "evidence": []}, "yen_carry_risk": {"status": "ACTIVE", "score": 0.0, "ewj_change_pct": -2.099, "vxx_change_pct": 1.605, "evidence": ["EWJ -2.1% (Japan/Nikkei weak — yen carry stress)"]}, "cio_action": "NO_ADD", "blocked_actions": [], "notes": []}