{"thesis_id": "THESIS-HAWKISH-WARSH-FED", "generated_at": "2026-07-07 23:22 SGT", "status": "WARNING", "score": 43.5, "fed_tone": {"status": "UNKNOWN", "score": 10.0, "hawkish_count": 0, "dovish_count": 0, "evidence": ["No Fed/macro keywords found in recent headlines — neutral assumed"]}, "rates_confirmation": {"status": "WATCH", "score": 9.5, "tlt_change_pct": -0.676, "ief_change_pct": -0.281, "shy_change_pct": -0.043, "us_10y_proxy": 0.01, "us_30y_proxy": 0.01, "us_10y_level": 4.49, "us_30y_level": 4.98, "yield_snapshot_date": "2026-07-07", "yield_previous_snapshot_date": "2026-07-06", "yield_delta_source": "FRED_DB_HISTORY", "evidence": ["TLT -0.7% (rate pressure active)", "FRED levels: 10Y 4.49%, 30Y 4.98%"]}, "dollar_confirmation": {"status": "WATCH", "score": 6.0, "uup_change_pct": 0.142, "evidence": ["UUP +0.1% (mild USD support)"]}, "bank_confirmation": {"status": "WATCH", "score": 8.5, "xlf_change_pct": 0.196, "jpm_change_pct": 0.219, "bac_change_pct": 0.392, "wfc_change_pct": -0.034, "gs_change_pct": -1.608, "ms_change_pct": -0.655, "credit_stress": false, "hyg_change_pct": -0.131, "jnk_change_pct": -0.12, "evidence": []}, "gold_miner_confirmation": {"status": "FAIL", "score": 1.5, "gld_change_pct": -0.447, "slv_change_pct": -2.174, "gdx_change_pct": -3.327, "gdxj_change_pct": -4.148, "au_change_pct": -2.832, "nem_change_pct": -3.625, "gdx_vs_gld_spread": -2.88, "evidence": ["GDX -3.3% (miners breaking down)", "AU/NEM avg -3.2% (portfolio miners weak)"]}, "high_beta_risk": {"status": "WATCH", "score": 3.0, "qqq_change_pct": -2.197, "iwm_change_pct": -0.78, "vxx_change_pct": 1.815, "uvxy_change_pct": 2.774, "nvda_change_pct": -1.381, "red_flag": false, "evidence": ["QQQ -2.2% (tech selling under hawkish)"]}, "credit_stress": {"status": "WATCH", "score": 5.0, "hyg_change_pct": -0.131, "jnk_change_pct": -0.12, "lqd_change_pct": -0.538, "evidence": []}, "yen_carry_risk": {"status": "ACTIVE", "score": 0.0, "ewj_change_pct": -2.173, "vxx_change_pct": 1.815, "evidence": ["EWJ -2.2% (Japan/Nikkei weak — yen carry stress)"]}, "cio_action": "NO_ADD", "blocked_actions": [], "notes": []}